{"features":[{"geometry":{"coordinates":[6.560287,0.310119],"type":"Point"},"id":"wattlas-plant-osm-relation-17657273","properties":{"aliases":["Aproveitamento Hidroelétrico do Contador"],"canonicalAnchor":"osm:relation/17657273","canonicalCountryKey":"ST","capacityMw":0.0,"country":"ST","externalIds":{"osm":"relation/17657273"},"geographyId":"ST-19237168B40253326356618","id":"wattlas-plant-osm-relation-17657273","lifecycleCounts":{"operational":1},"locationPrecision":"exact","name":"Aproveitamento Hidroelétrico do Contador","operatingCapacityCoverage":{"coveragePercent":0.0,"knownUnitCount":0,"method":"unavailable","totalUnitCount":0},"operatingCapacityMw":0.0,"operatingCapacityMwByTechnology":{},"plannedCapacityCoverage":{"coveragePercent":0.0,"knownUnitCount":0,"method":"unavailable","totalUnitCount":0},"plannedCapacityMw":0.0,"plannedCapacityMwByTechnology":{},"recordCount":1,"recordIds":["wattlas-record-osm-relation-17657273"],"sourceIds":["openstreetmap-power"],"technologies":["hydro"],"technologyMixMw":{"hydro":0.0},"unitCount":0,"unitIds":[]},"type":"Feature"},{"geometry":{"coordinates":[6.70676,0.321946],"type":"Point"},"id":"wattlas-plant-osm-way-1293571064","properties":{"aliases":["Térmica Bobô Fôrro"],"canonicalAnchor":"osm:way/1293571064","canonicalCountryKey":"ST","capacityMw":4.0,"country":"ST","externalIds":{"osm":"way/1293571064"},"geographyId":"ST-19237168B40253326356618","id":"wattlas-plant-osm-way-1293571064","lifecycleCounts":{"operational":1},"locationPrecision":"exact","name":"Térmica Bobô Fôrro","operatingCapacityCoverage":{"coveragePercent":100.0,"knownUnitCount":0,"method":"plant_aggregate","provenance":{"evidenceCount":0,"recordIds":["wattlas-record-osm-way-1293571064"],"sourceIds":["openstreetmap-power"],"sourceTypes":["community_mapped"],"valueKind":"reported"},"totalUnitCount":0},"operatingCapacityMw":4.0,"operatingCapacityMwByTechnology":{"other":4.0},"plannedCapacityCoverage":{"coveragePercent":0.0,"knownUnitCount":0,"method":"unavailable","totalUnitCount":0},"plannedCapacityMw":0.0,"plannedCapacityMwByTechnology":{},"recordCount":1,"recordIds":["wattlas-record-osm-way-1293571064"],"sourceIds":["openstreetmap-power"],"technologies":["other"],"technologyMixMw":{"other":4.0},"unitCount":0,"unitIds":[]},"type":"Feature"}],"type":"FeatureCollection"}