{"features":[{"geometry":{"coordinates":[-175.035002,-21.153371],"type":"Point"},"id":"wattlas-plant-osm-relation-15464020","properties":{"aliases":["Manumataongo Wind Farm"],"canonicalAnchor":"osm:relation/15464020","canonicalCountryKey":"TO","capacityMw":0.0,"country":"TO","externalIds":{"osm":"relation/15464020"},"geographyId":"TO-12702645B50986277851262","id":"wattlas-plant-osm-relation-15464020","lifecycleCounts":{"operational":1},"locationPrecision":"exact","name":"Manumataongo Wind Farm","operatingCapacityCoverage":{"coveragePercent":0.0,"knownUnitCount":0,"method":"unavailable","totalUnitCount":0},"operatingCapacityMw":0.0,"operatingCapacityMwByTechnology":{},"plannedCapacityCoverage":{"coveragePercent":0.0,"knownUnitCount":0,"method":"unavailable","totalUnitCount":0},"plannedCapacityMw":0.0,"plannedCapacityMwByTechnology":{},"recordCount":1,"recordIds":["wattlas-record-osm-relation-15464020"],"sourceIds":["openstreetmap-power"],"technologies":["wind"],"technologyMixMw":{"wind":0.0},"unitCount":0,"unitIds":[]},"type":"Feature"}],"type":"FeatureCollection"}