{"features":[{"geometry":{"coordinates":[44.923631,12.824969],"type":"Point"},"id":"wattlas-plant-osm-way-121834063","properties":{"aliases":["محطة الحسوة البخارية"],"canonicalAnchor":"osm:way/121834063","canonicalCountryKey":"YE","capacityMw":0.0,"country":"YE","externalIds":{"osm":"way/121834063"},"geographyId":"YE-18629408B11945654439238","id":"wattlas-plant-osm-way-121834063","lifecycleCounts":{"operational":1},"locationPrecision":"exact","name":"محطة الحسوة البخارية","operatingCapacityCoverage":{"coveragePercent":0.0,"knownUnitCount":0,"method":"unavailable","totalUnitCount":0},"operatingCapacityMw":0.0,"operatingCapacityMwByTechnology":{},"plannedCapacityCoverage":{"coveragePercent":0.0,"knownUnitCount":0,"method":"unavailable","totalUnitCount":0},"plannedCapacityMw":0.0,"plannedCapacityMwByTechnology":{},"recordCount":1,"recordIds":["wattlas-record-osm-way-121834063"],"sourceIds":["openstreetmap-power"],"technologies":["other"],"technologyMixMw":{"other":0.0},"unitCount":0,"unitIds":[]},"type":"Feature"},{"geometry":{"coordinates":[44.919926,12.825525],"type":"Point"},"id":"wattlas-plant-osm-way-1250586199","properties":{"aliases":["Aden power station"],"canonicalAnchor":"osm:way/1250586199","canonicalCountryKey":"YE","capacityMw":264.0,"country":"YE","externalIds":{"osm":"way/1250586199"},"geographyId":"YE-18629408B11945654439238","id":"wattlas-plant-osm-way-1250586199","lifecycleCounts":{"operational":1},"locationPrecision":"exact","name":"Aden power station","operatingCapacityCoverage":{"coveragePercent":100.0,"knownUnitCount":0,"method":"plant_aggregate","provenance":{"evidenceCount":0,"recordIds":["wattlas-record-osm-way-1250586199"],"sourceIds":["openstreetmap-power"],"sourceTypes":["community_mapped"],"valueKind":"reported"},"totalUnitCount":0},"operatingCapacityMw":264.0,"operatingCapacityMwByTechnology":{"gas":264.0},"plannedCapacityCoverage":{"coveragePercent":0.0,"knownUnitCount":0,"method":"unavailable","totalUnitCount":0},"plannedCapacityMw":0.0,"plannedCapacityMwByTechnology":{},"recordCount":1,"recordIds":["wattlas-record-osm-way-1250586199"],"sourceIds":["openstreetmap-power"],"technologies":["gas"],"technologyMixMw":{"gas":264.0},"unitCount":0,"unitIds":[]},"type":"Feature"},{"geometry":{"coordinates":[44.270412,15.244608],"type":"Point"},"id":"wattlas-plant-osm-way-249334707","properties":{"aliases":["محطة حزيز"],"canonicalAnchor":"osm:way/249334707","canonicalCountryKey":"YE","capacityMw":0.0,"country":"YE","externalIds":{"osm":"way/249334707"},"geographyId":"YE-18629408B64822604790923","id":"wattlas-plant-osm-way-249334707","lifecycleCounts":{"operational":1},"locationPrecision":"exact","name":"محطة حزيز","operatingCapacityCoverage":{"coveragePercent":0.0,"knownUnitCount":0,"method":"unavailable","totalUnitCount":0},"operatingCapacityMw":0.0,"operatingCapacityMwByTechnology":{},"plannedCapacityCoverage":{"coveragePercent":0.0,"knownUnitCount":0,"method":"unavailable","totalUnitCount":0},"plannedCapacityMw":0.0,"plannedCapacityMwByTechnology":{},"recordCount":1,"recordIds":["wattlas-record-osm-way-249334707"],"sourceIds":["openstreetmap-power"],"technologies":["oil"],"technologyMixMw":{"oil":0.0},"unitCount":0,"unitIds":[]},"type":"Feature"},{"geometry":{"coordinates":[45.771311,15.552255],"type":"Point"},"id":"wattlas-plant-osm-way-726183976","properties":{"aliases":["Marib Power Plant"],"canonicalAnchor":"osm:way/726183976","canonicalCountryKey":"YE","capacityMw":0.0,"country":"YE","externalIds":{"osm":"way/726183976"},"geographyId":"YE-18629408B1777518619063","id":"wattlas-plant-osm-way-726183976","lifecycleCounts":{"operational":1},"locationPrecision":"exact","name":"Marib Power Plant","operatingCapacityCoverage":{"coveragePercent":0.0,"knownUnitCount":0,"method":"unavailable","totalUnitCount":0},"operatingCapacityMw":0.0,"operatingCapacityMwByTechnology":{},"plannedCapacityCoverage":{"coveragePercent":0.0,"knownUnitCount":0,"method":"unavailable","totalUnitCount":0},"plannedCapacityMw":0.0,"plannedCapacityMwByTechnology":{},"recordCount":1,"recordIds":["wattlas-record-osm-way-726183976"],"sourceIds":["openstreetmap-power"],"technologies":["gas"],"technologyMixMw":{"gas":0.0},"unitCount":0,"unitIds":[]},"type":"Feature"}],"type":"FeatureCollection"}