{"features":[{"geometry":{"coordinates":[125.689511,-8.539748],"type":"Point"},"id":"wattlas-plant-osm-way-152632845","properties":{"aliases":["Usina de Petróleo de Hera"],"canonicalAnchor":"osm:way/152632845","canonicalCountryKey":"TL","capacityMw":119.0,"country":"TL","externalIds":{"osm":"way/152632845"},"geographyId":"TL-58719522B43373882655947","id":"wattlas-plant-osm-way-152632845","lifecycleCounts":{"operational":1},"locationPrecision":"exact","name":"Usina de Petróleo de Hera","operatingCapacityCoverage":{"coveragePercent":100.0,"knownUnitCount":0,"method":"plant_aggregate","provenance":{"evidenceCount":0,"recordIds":["wattlas-record-osm-way-152632845"],"sourceIds":["openstreetmap-power"],"sourceTypes":["community_mapped"],"valueKind":"reported"},"totalUnitCount":0},"operatingCapacityMw":119.0,"operatingCapacityMwByTechnology":{"oil":119.0},"plannedCapacityCoverage":{"coveragePercent":0.0,"knownUnitCount":0,"method":"unavailable","totalUnitCount":0},"plannedCapacityMw":0.0,"plannedCapacityMwByTechnology":{},"recordCount":1,"recordIds":["wattlas-record-osm-way-152632845"],"sourceIds":["openstreetmap-power"],"technologies":["oil"],"technologyMixMw":{"oil":119.0},"unitCount":0,"unitIds":[]},"type":"Feature"},{"geometry":{"coordinates":[125.7346,-9.154102],"type":"Point"},"id":"wattlas-plant-wikidata-q28870383","properties":{"aliases":["Betano Power Plant"],"canonicalAnchor":"wikidata:Q28870383","canonicalCountryKey":"TL","capacityMw":136.0,"country":"TL","externalIds":{"osm":"way/569852976","wikidata":"Q28870383"},"geographyId":"TL-58719522B42816757733835","id":"wattlas-plant-wikidata-q28870383","idAliases":["wattlas-plant-osm-way-569852976"],"lifecycleCounts":{"operational":1},"locationPrecision":"exact","name":"Betano Power Plant","operatingCapacityCoverage":{"coveragePercent":100.0,"knownUnitCount":0,"method":"plant_aggregate","provenance":{"evidenceCount":0,"recordIds":["wattlas-record-osm-way-569852976"],"sourceIds":["openstreetmap-power"],"sourceTypes":["community_mapped"],"valueKind":"reported"},"totalUnitCount":0},"operatingCapacityMw":136.0,"operatingCapacityMwByTechnology":{"oil":136.0},"plannedCapacityCoverage":{"coveragePercent":0.0,"knownUnitCount":0,"method":"unavailable","totalUnitCount":0},"plannedCapacityMw":0.0,"plannedCapacityMwByTechnology":{},"recordCount":1,"recordIds":["wattlas-record-osm-way-569852976"],"sourceIds":["openstreetmap-power"],"technologies":["oil"],"technologyMixMw":{"oil":136.0},"unitCount":0,"unitIds":[]},"type":"Feature"}],"type":"FeatureCollection"}